LICENSE
README.md
setup.py
writefull/__init__.py
writefull.egg-info/PKG-INFO
writefull.egg-info/SOURCES.txt
writefull.egg-info/dependency_links.txt
writefull.egg-info/top_level.txt